dater/__about__.py
dater/__init__.py
dater/py.typed
dater-0.1.0.dist-info/METADATA
dater-0.1.0.dist-info/WHEEL
dater-0.1.0.dist-info/entry_points.txt
dater-0.1.0.dist-info/RECORD
