Metadata-Version: 2.4
Name: dater
Version: 0.1.0
Summary: Dater? I hardly know 'er!
Project-URL: Documentation, https://github.com/educationwarehouse/dater#readme
Project-URL: Issues, https://github.com/educationwarehouse/dater/issues
Project-URL: Source, https://github.com/educationwarehouse/dater
Author-email: Robin van der Noord <robinvandernoord@gmail.com>
Requires-Python: >=3.13
Requires-Dist: ewok<1
